nlgm/__init__.py
nlgm/autoencoder.py
nlgm/manifolds.py
nlgm/optimizers.py
nlgm/searchspace.py
nlgm/train.py
nlgm/visualize.py
nlgm-0.1.0.dist-info/LICENSE
nlgm-0.1.0.dist-info/METADATA
nlgm-0.1.0.dist-info/WHEEL
nlgm-0.1.0.dist-info/top_level.txt
nlgm-0.1.0.dist-info/RECORD
