Metadata-Version: 2.1
Name: nlgm
Version: 0.1.0
Summary: Implementation of the neural latent geometry search framework
Author-email: Anupam Bhakta <ab5494@columbia.edu>, Adam Mehdi <adm2243@columbia.edu>, Kevin Qiu <kzq2000@columbia.edu>
License: MIT License
Project-URL: Homepage, https://github.com/ae-bii/nlgm
Project-URL: Issues, https://github.com/ae-bii/nlgm/issues
Classifier: Programming Language :: Python :: 3
Classifier: License :: OSI Approved :: MIT License
Classifier: Operating System :: OS Independent
Requires-Python: >=3.8
License-File: LICENSE
